{"batch_id":"2025-03-c652e21c","mode":"ai-first","pre_escrow":true,"id":"D787546ec","status":"ready","subject":{"patient_id":"PT-05036"},"inputs":{"evidence":{"age":70,"chief_complaint":"suspected infection","vitals":{"heart_rate_bpm":129,"map_mmhg":69,"temp_c":38.85,"resp_rate":18,"spo2_pct":96},"labs":{"wbc_k_ul":15.31,"lactate_mmol_l":2.3},"sepsis_probability_score":0.42},"metadata":{"admitted_at":"2025-03-16T01:21:06Z","ward":"medical-surgical"}},"ledger":[{"entry_id":"evt-0001","timestamp":"2025-03-16T01:21:09Z","event":"state_transition","from":null,"to":"in-prep"},{"entry_id":"evt-0002","timestamp":"2025-03-16T01:25:06Z","event":"state_transition","from":"in-prep","to":"ready"}]}