{"batch_id":"2025-04-9b71dbb3","mode":"human-only","pre_escrow":false,"id":"D91a20f68","status":"closed","subject":{"patient_id":"PT-05043"},"inputs":{"evidence":{"age":68,"chief_complaint":"shortness of breath","vitals":{"heart_rate_bpm":139,"map_mmhg":67,"temp_c":37.71,"resp_rate":15,"spo2_pct":91},"labs":{"wbc_k_ul":18.08,"lactate_mmol_l":1.55},"sepsis_probability_score":0.94},"metadata":{"admitted_at":"2025-04-13T01:06:42Z","ward":"ICU"}},"ledger":[{"entry_id":"evt-0001","timestamp":"2025-04-13T01:06:45Z","event":"state_transition","from":null,"to":"in-prep"},{"entry_id":"evt-0002","timestamp":"2025-04-13T01:10:42Z","event":"state_transition","from":"in-prep","to":"ready"},{"entry_id":"evt-0003","timestamp":"2025-04-13T06:19:42Z","event":"decision","author":{"type":"human","id":"charge.nurse@kurson-health.org"},"verdict":"yes","rationale":"Clinical presentation consistent with sepsis — initiating Sepsis-3 bundle."},{"entry_id":"evt-0004","timestamp":"2025-04-13T06:21:42Z","event":"state_transition","from":"ready","to":"closed"}]}